len8/__init__.py
len8/__main__.py
len8/checker.py
len8/cli.py
len8/errors.py
len8/py.typed
len8-0.7.3.post0.dist-info/LICENSE
len8-0.7.3.post0.dist-info/METADATA
len8-0.7.3.post0.dist-info/WHEEL
len8-0.7.3.post0.dist-info/entry_points.txt
len8-0.7.3.post0.dist-info/top_level.txt
len8-0.7.3.post0.dist-info/RECORD
