Metadata-Version: 2.1
Name: len8
Version: 0.7.3.post0
Summary: A utility for keeping line lengths within PEP 8 standards.
Home-page: https://github.com/parafoxia/len8
Author: Ethan Henderson, Jonxslays
License: BSD-3-Clause
Project-URL: Documentation, https://len8.readthedocs.io/en/latest/
Project-URL: Source, https://github.com/parafoxia/len8
Project-URL: Bug Tracker, https://github.com/parafoxia/len8/issues
Project-URL: CI, https://github.com/parafoxia/len8/actions
Project-URL: Changelog, https://github.com/parafoxia/len8/releases
Platform: UNKNOWN
Classifier: Development Status :: 3 - Alpha
Classifier: Environment :: Console
Classifier: Intended Audience :: Developers
Classifier: License :: OSI Approved :: BSD License
Classifier: Natural Language :: English
Classifier: Operating System :: MacOS
Classifier: Operating System :: Microsoft :: Windows
Classifier: Operating System :: OS Independent
Classifier: Operating System :: POSIX
Classifier: Operating System :: Unix
Classifier: Programming Language :: Python :: 3
Classifier: Programming Language :: Python :: 3 :: Only
Classifier: Programming Language :: Python :: 3.6
Classifier: Programming Language :: Python :: 3.7
Classifier: Programming Language :: Python :: 3.8
Classifier: Programming Language :: Python :: 3.9
Classifier: Programming Language :: Python :: 3.10
Classifier: Programming Language :: Python :: Implementation :: CPython
Classifier: Topic :: Utilities
Classifier: Typing :: Typed
Requires-Python: >=3.6.0,<3.12
License-File: LICENSE
Requires-Dist: click (<9,>=8)
Requires-Dist: toml (~=0.10.2)
